{
  "id": "pkg:maven/it.unibo.collektive.collektivize/it.unibo.collektive.collektivize.gradle.plugin",
  "description": "This plugin generates a \"fielded\" version of any Kotlin library.",
  "group_id": "it.unibo.collektive.collektivize",
  "artifact_id": "it.unibo.collektive.collektivize.gradle.plugin",
  "version_latest": "27.0.1-dev05+c42365d",
  "ts_publish": 1756249493000,
  "dt_publish": "2025-08-27 07:04:53.000",
  "ts_update": 1756250751855,
  "dt_update": "2025-08-27 07:25:51.855",
  "count_dep": 1,
  "count_ref": 0,
  "licenses": [
    "Apache License, Version 2.0"
  ],
  "categories": null,
  "dsv": 1
}