{
  "id": "pkg:maven/org.jetbrains.kotlin-wrappers/kotlin-mui-icons-material",
  "description": "Kotlin wrapper for Material UI Icons",
  "group_id": "org.jetbrains.kotlin-wrappers",
  "artifact_id": "kotlin-mui-icons-material",
  "version_latest": "2025.9.6-5.18.0",
  "ts_publish": 1757569859000,
  "dt_publish": "2025-09-11 13:50:59.000",
  "ts_update": 1757571754719,
  "dt_update": "2025-09-11 14:22:34.719",
  "count_dep": 1,
  "count_ref": 0,
  "licenses": [
    "The Apache License, Version 2.0"
  ],
  "categories": [
    "Uncategorized"
  ],
  "dsv": 1
}