{
  "id": "pkg:maven/org.eclipse.dirigible/dirigible-components-template-application-dao",
  "description": null,
  "group_id": "org.eclipse.dirigible",
  "artifact_id": "dirigible-components-template-application-dao",
  "version_latest": "12.9.0",
  "ts_publish": 1754992421000,
  "dt_publish": "2025-08-12 17:53:41.000",
  "ts_update": 1754993853817,
  "dt_update": "2025-08-12 18:17:33.817",
  "count_dep": 0,
  "count_ref": 2,
  "licenses": [],
  "categories": [
    "Uncategorized"
  ],
  "dsv": 1
}