{
  "id": "pkg:maven/org.eclipse.dirigible/dirigible-database-sql-mysql",
  "description": "Core modules packaged with Dirigible",
  "group_id": "org.eclipse.dirigible",
  "artifact_id": "dirigible-database-sql-mysql",
  "version_latest": "12.16.0",
  "ts_publish": 1758281903000,
  "dt_publish": "2025-09-19 19:38:23.000",
  "ts_update": 1758282972930,
  "dt_update": "2025-09-19 19:56:12.930",
  "count_dep": 114,
  "count_ref": 1,
  "licenses": [
    "Eclipse Public License - v 2.0"
  ],
  "categories": [
    "Uncategorized"
  ],
  "dsv": 1
}