{
  "id": "pkg:maven/com.bullhorn/sdk-rest",
  "description": "The Bullhorn REST SDK provides simple authentication to the Bullhorn REST APIs as well as wrapper\n        objects for the API itself and all domain objects. It is typically used for integrating or customizing the\n        Bullhorn ATS platform.",
  "group_id": "com.bullhorn",
  "artifact_id": "sdk-rest",
  "version_latest": "2.5.3",
  "ts_publish": 1756824743000,
  "dt_publish": "2025-09-02 22:52:23.000",
  "ts_update": 1756826182214,
  "dt_update": "2025-09-02 23:16:22.214",
  "count_dep": 46,
  "count_ref": 0,
  "licenses": [
    "MIT License"
  ],
  "categories": [
    "Cloud Computing"
  ],
  "dsv": 1
}