{
  "id": "pkg:maven/io.dropwizard.metrics5/metrics-annotation",
  "description": "A dependency-less package of just the annotations used by other Metrics modules.",
  "group_id": "io.dropwizard.metrics5",
  "artifact_id": "metrics-annotation",
  "version_latest": "5.0.4",
  "ts_publish": 1756669811000,
  "dt_publish": "2025-09-01 03:50:11.000",
  "ts_update": 1756671953014,
  "dt_update": "2025-09-01 04:25:53.014",
  "count_dep": 0,
  "count_ref": 9,
  "licenses": [
    "Apache License 2.0"
  ],
  "categories": [
    "Uncategorized"
  ],
  "dsv": 1
}