{
  "id": "pkg:maven/cn.hdfk7.boot/hdfk7-boot-starter-discovery",
  "description": "基于nacos实现的服务发现、配置中心功能，提供服务上下线立即同步刷新路由缓存的能力。",
  "group_id": "cn.hdfk7.boot",
  "artifact_id": "hdfk7-boot-starter-discovery",
  "version_latest": "3.0.0",
  "ts_publish": 1756578721000,
  "dt_publish": "2025-08-31 02:32:01.000",
  "ts_update": 1756579202603,
  "dt_update": "2025-08-31 02:40:02.603",
  "count_dep": 128,
  "count_ref": 0,
  "licenses": [
    "Apache License, Version 2.0"
  ],
  "categories": null,
  "dsv": 1
}