{
  "id": "pkg:maven/io.github.jdumasleon/jarvis-android-sdk",
  "description": "Android SDK for Jarvis network inspection and debugging toolkit",
  "group_id": "io.github.jdumasleon",
  "artifact_id": "jarvis-android-sdk",
  "version_latest": "1.1.5",
  "ts_publish": 1758314638000,
  "dt_publish": "2025-09-20 04:43:58.000",
  "ts_update": 1758316387110,
  "dt_update": "2025-09-20 05:13:07.110",
  "count_dep": 18,
  "count_ref": 0,
  "licenses": [
    "MIT License"
  ],
  "categories": null,
  "dsv": 1
}