{
  "id": "pkg:maven/edu.internet2.middleware.grouper/google-apps-provisioner",
  "description": "Google Apps Integration Library",
  "group_id": "edu.internet2.middleware.grouper",
  "artifact_id": "google-apps-provisioner",
  "version_latest": "4.19.1",
  "ts_publish": 1755443966000,
  "dt_publish": "2025-08-17 23:19:26.000",
  "ts_update": 1755444773865,
  "dt_update": "2025-08-17 23:32:53.865",
  "count_dep": 176,
  "count_ref": 0,
  "licenses": [
    "Apache 2"
  ],
  "categories": [
    "Data Management",
    "Database Access"
  ],
  "dsv": 1
}