{
	"id":"pkg:maven/net.datafaker/datafaker",
	"description":"This library is an improved fork of JavaFaker (as well as Ruby's stympy/faker gem and Perl's Data::Faker\n        library)\n        that generates fake data. It's useful when you're developing a new project and need some pretty data for\n        showcase.",
	"group_id":"net.datafaker",
	"artifact_id":"datafaker",
	"version_latest":"2.5.0",
	"ts_publish":1758030279000,
	"dt_publish":"2025-09-16 21:44:39.000",
	"ts_update":1758032221167,
	"dt_update":"2025-09-16 22:15:57.212",
	"count_dep":18,
	"count_ref":0,
	"licenses":[
		"The Apache Software License, Version 2.0"
	],
	"categories":[
		"Uncategorized"
	],
	"dsv":1,
	"url_project":"https://www.datafaker.net",
	"url_oss_index":"https://ossindex.sonatype.org/component/pkg:maven/net.datafaker/datafaker@2.5.0",
	"contributors":[
		"Erik Pragt"
	],
	"url_scm":"https://github.com/datafaker-net/datafaker"
}