{
	"id":"pkg:maven/io.quarkus/quarkus-oidc-redis-token-state-manager-parent",
	"group_id":"io.quarkus",
	"artifact_id":"quarkus-oidc-redis-token-state-manager-parent",
	"version_latest":"3.25.1",
	"ts_publish":1754489375000,
	"dt_publish":"2025-08-06 22:09:35.000",
	"ts_update":1754491690588,
	"dt_update":"2025-08-06 22:32:13.596",
	"count_dep":0,
	"count_ref":0,
	"licenses":[],
	"categories":[
		"Uncategorized"
	],
	"dsv":1,
	"url_oss_index":"https://ossindex.sonatype.org/component/pkg:maven/io.quarkus/quarkus-oidc-redis-token-state-manager-parent@3.25.1"
}