{
  "id": "pkg:maven/org.apache.camel.quarkus/camel-quarkus-azure-storage-blob",
  "description": "Store and retrieve blobs from Azure Storage Blob Service using SDK v12.",
  "group_id": "org.apache.camel.quarkus",
  "artifact_id": "camel-quarkus-azure-storage-blob",
  "version_latest": "3.26.0",
  "ts_publish": 1755762236000,
  "dt_publish": "2025-08-21 15:43:56.000",
  "ts_update": 1758385070741,
  "dt_update": "2025-09-21 00:17:50.741",
  "count_dep": 3,
  "count_ref": 0,
  "licenses": [],
  "categories": [
    "Uncategorized"
  ],
  "dsv": 1
}