{
  "id": "pkg:maven/com.uber.motif/motif-ast-intellij",
  "description": "Simple DI API for Android / Java.",
  "group_id": "com.uber.motif",
  "artifact_id": "motif-ast-intellij",
  "version_latest": "0.4.0-alpha08",
  "ts_publish": 1758661640000,
  "dt_publish": "2025-09-24 05:07:20.000",
  "ts_update": 1758662765946,
  "dt_update": "2025-09-24 05:26:05.946",
  "count_dep": 6,
  "count_ref": 1,
  "licenses": [
    "The Apache Software License, Version 2.0"
  ],
  "categories": [
    "Uncategorized"
  ],
  "dsv": 1
}