{
  "id": "pkg:maven/cn.web3er.wrench/whn-wrench-starter-dynamic-config-center",
  "description": "whn wrench modules dynamic config center",
  "group_id": "cn.web3er.wrench",
  "artifact_id": "whn-wrench-starter-dynamic-config-center",
  "version_latest": "1.6",
  "ts_publish": 1755661487000,
  "dt_publish": "2025-08-20 11:44:47.000",
  "ts_update": 1755663668353,
  "dt_update": "2025-08-20 12:21:08.353",
  "count_dep": 9,
  "count_ref": 1,
  "licenses": [
    "Apache License"
  ],
  "categories": null,
  "dsv": 1
}