{
  "id": "pkg:maven/io.gravitee.apim.rest.api/gravitee-apim-rest-api-service",
  "description": "Gravitee IO Manager Service",
  "group_id": "io.gravitee.apim.rest.api",
  "artifact_id": "gravitee-apim-rest-api-service",
  "version_latest": "4.8.4",
  "ts_publish": 1755198769000,
  "dt_publish": "2025-08-15 03:12:49.000",
  "ts_update": 1755199548232,
  "dt_update": "2025-08-15 03:25:48.232",
  "count_dep": 413,
  "count_ref": 26,
  "licenses": [
    "Apache License, Version 2.0"
  ],
  "categories": [
    "Uncategorized"
  ],
  "dsv": 1
}