{
  "id": "pkg:maven/org.scala-sbt/launcher-interface",
  "description": "Interfaces for launching projects with the sbt launcher",
  "group_id": "org.scala-sbt",
  "artifact_id": "launcher-interface",
  "version_latest": "1.5.0",
  "ts_publish": 1757193022000,
  "dt_publish": "2025-09-07 05:10:22.000",
  "ts_update": 1757195049086,
  "dt_update": "2025-09-07 05:44:09.086",
  "count_dep": 0,
  "count_ref": 0,
  "licenses": [
    "Apache-2.0"
  ],
  "categories": [
    "Build Tools"
  ],
  "dsv": 1
}