{
  "id": "pkg:maven/app.photofox.vips-ffm/vips-ffm-core",
  "description": "libvips for JVM projects, using JDK 22's FFM and Class-File APIs to generate complete, safe, and fast bindings for image manipulation",
  "group_id": "app.photofox.vips-ffm",
  "artifact_id": "vips-ffm-core",
  "version_latest": "1.9.1",
  "ts_publish": 1756654404000,
  "dt_publish": "2025-08-31 23:33:24.000",
  "ts_update": 1756655044230,
  "dt_update": "2025-08-31 23:44:04.230",
  "count_dep": 0,
  "count_ref": 0,
  "licenses": [
    "Apache License, Version 2.0"
  ],
  "categories": null,
  "dsv": 1
}