{
  "id": "pkg:maven/software.amazon.awssdk/b2bi",
  "description": "The AWS Java SDK for B2 Bi module holds the client classes that are used for\n        communicating with B2 Bi.",
  "group_id": "software.amazon.awssdk",
  "artifact_id": "b2bi",
  "version_latest": "2.32.27",
  "ts_publish": 1755727133000,
  "dt_publish": "2025-08-21 05:58:53.000",
  "ts_update": 1755728766006,
  "dt_update": "2025-08-21 06:26:06.006",
  "count_dep": 3,
  "count_ref": 1,
  "licenses": [],
  "categories": [
    "Software Development Kit"
  ],
  "dsv": 1
}