{
  "id": "pkg:maven/software.amazon.awssdk/cloud9",
  "description": "The AWS Java SDK for AWS Cloud9 module holds the client classes that are used for communicating\n        with AWS Cloud9 Service",
  "group_id": "software.amazon.awssdk",
  "artifact_id": "cloud9",
  "version_latest": "2.33.11",
  "ts_publish": 1758058461000,
  "dt_publish": "2025-09-17 05:34:21.000",
  "ts_update": 1758059764427,
  "dt_update": "2025-09-17 05:56:04.427",
  "count_dep": 3,
  "count_ref": 0,
  "licenses": [],
  "categories": [
    "Software Development Kit"
  ],
  "dsv": 1
}