{
  "id": "pkg:maven/software.amazon.awssdk/codeguruprofiler",
  "description": "The AWS Java SDK for CodeGuruProfiler module holds the client classes that are used for\n        communicating with CodeGuruProfiler.",
  "group_id": "software.amazon.awssdk",
  "artifact_id": "codeguruprofiler",
  "version_latest": "2.32.18",
  "ts_publish": 1754610673000,
  "dt_publish": "2025-08-08 07:51:13.000",
  "ts_update": 1754612766503,
  "dt_update": "2025-08-08 08:26:06.503",
  "count_dep": 33,
  "count_ref": 1,
  "licenses": [],
  "categories": [
    "Software Development Kit"
  ],
  "dsv": 1
}