{
  "id": "pkg:maven/org.apache.nifi/nifi-windows-event-log-processors",
  "description": "NiFi Extensions Bill of Materials",
  "group_id": "org.apache.nifi",
  "artifact_id": "nifi-windows-event-log-processors",
  "version_latest": "2.5.0",
  "ts_publish": 1752929388000,
  "dt_publish": "2025-07-19 20:49:48.000",
  "ts_update": 1756570616564,
  "dt_update": "2025-08-31 00:16:56.564",
  "count_dep": 70,
  "count_ref": 2,
  "licenses": [
    "Apache License, Version 2.0"
  ],
  "categories": [
    "Analytics"
  ],
  "dsv": 1
}