{
  "id": "pkg:maven/io.github.dkmarkell/textresource-compose",
  "description": "Jetpack Compose extensions for TextResource: resolve strings in composition and remember definitions efficiently, pairing with the core module.",
  "group_id": "io.github.dkmarkell",
  "artifact_id": "textresource-compose",
  "version_latest": "0.3.0",
  "ts_publish": 1755991542000,
  "dt_publish": "2025-08-24 07:25:42.000",
  "ts_update": 1755992655072,
  "dt_update": "2025-08-24 07:44:15.072",
  "count_dep": 5,
  "count_ref": 0,
  "licenses": [
    "MIT License"
  ],
  "categories": null,
  "dsv": 1
}