{
  "id": "pkg:maven/com.netflix.graphql.dgs/graphql-dgs-client",
  "description": "graphql-dgs-client",
  "group_id": "com.netflix.graphql.dgs",
  "artifact_id": "graphql-dgs-client",
  "version_latest": "10.4.0",
  "ts_publish": 1757967603000,
  "dt_publish": "2025-09-16 04:20:03.000",
  "ts_update": 1757969109548,
  "dt_update": "2025-09-16 04:45:09.548",
  "count_dep": 13,
  "count_ref": 1,
  "licenses": [
    "The Apache Software License, Version 2.0"
  ],
  "categories": [
    "Uncategorized"
  ],
  "dsv": 1
}