{
  "id": "pkg:maven/name.remal.gradle-plugins.toolkit/toolkit",
  "description": "remal-gradle-plugins: toolkit: toolkit",
  "group_id": "name.remal.gradle-plugins.toolkit",
  "artifact_id": "toolkit",
  "version_latest": "0.74.0",
  "ts_publish": 1759095483000,
  "dt_publish": "2025-09-29 05:38:03.000",
  "ts_update": 1759096572658,
  "dt_update": "2025-09-29 05:56:12.658",
  "count_dep": 0,
  "count_ref": 1,
  "licenses": [
    "MIT License"
  ],
  "categories": [
    "Uncategorized"
  ],
  "dsv": 1
}