{
  "id": "pkg:maven/com.squareup.misk.schema-migrator/com.squareup.misk.schema-migrator.gradle.plugin",
  "description": "Open source application container in Kotlin",
  "group_id": "com.squareup.misk.schema-migrator",
  "artifact_id": "com.squareup.misk.schema-migrator.gradle.plugin",
  "version_latest": "2025.09.03.220355-71e5a9f",
  "ts_publish": 1756938466000,
  "dt_publish": "2025-09-04 06:27:46.000",
  "ts_update": 1756939460543,
  "dt_update": "2025-09-04 06:44:20.543",
  "count_dep": 6,
  "count_ref": 0,
  "licenses": [
    "The Apache Software License, Version 2.0"
  ],
  "categories": null,
  "dsv": 1
}