{
  "id": "pkg:maven/io.github.lyxnx.compose.ui/ui-wasm-js",
  "description": "Jetpack Compose UI extensions and utilities",
  "group_id": "io.github.lyxnx.compose.ui",
  "artifact_id": "ui-wasm-js",
  "version_latest": "2.2.40",
  "ts_publish": 1754649365000,
  "dt_publish": "2025-08-08 18:36:05.000",
  "ts_update": 1754649867774,
  "dt_update": "2025-08-08 18:44:27.774",
  "count_dep": 7,
  "count_ref": 0,
  "licenses": [
    "Apache License, Version 2.0"
  ],
  "categories": null,
  "dsv": 1
}