{
	"id":"pkg:maven/io.github.jinghui70/rainbow-dbaccess",
	"description":"A powerful database access tool with ORM support, built on Spring JDBC.",
	"group_id":"io.github.jinghui70",
	"artifact_id":"rainbow-dbaccess",
	"version_latest":"6.0.2",
	"ts_publish":1756814496000,
	"dt_publish":"2025-09-02 20:01:36.000",
	"ts_update":1756816083929,
	"dt_update":"2025-09-02 20:26:04.208",
	"count_dep":16,
	"count_ref":0,
	"licenses":[
		"MIT License"
	],
	"dsv":1,
	"url_project":"https://github.com/jinghui70/rainbow-dbaccess",
	"url_oss_index":"https://ossindex.sonatype.org/component/pkg:maven/io.github.jinghui70/rainbow-dbaccess@6.0.2",
	"url_issue_management":"https://github.com/jinghui70/rainbow-dbaccess/issues",
	"contributors":[
		"Jinghui Li"
	],
	"url_scm":"https://github.com/jinghui70/rainbow-dbaccess"
}