{
  "id": "pkg:maven/org.apache.karaf.webconsole/org.apache.karaf.webconsole.features",
  "description": "This bundle provides Karaf features plugin for the Web Console.",
  "group_id": "org.apache.karaf.webconsole",
  "artifact_id": "org.apache.karaf.webconsole.features",
  "version_latest": "4.4.8",
  "ts_publish": 1754202355000,
  "dt_publish": "2025-08-03 14:25:55.000",
  "ts_update": 1758384991444,
  "dt_update": "2025-09-21 00:16:31.444",
  "count_dep": 24,
  "count_ref": 1,
  "licenses": [
    "Apache-2.0"
  ],
  "categories": [
    "Console"
  ],
  "dsv": 1
}