{
  "id": "pkg:maven/org.noear/luffy.executor.s.python",
  "description": "Java project for luffy",
  "group_id": "org.noear",
  "artifact_id": "luffy.executor.s.python",
  "version_latest": "1.10.0",
  "ts_publish": 1759337939000,
  "dt_publish": "2025-10-02 00:58:59.000",
  "ts_update": 1759338824671,
  "dt_update": "2025-10-02 01:13:44.671",
  "count_dep": 7,
  "count_ref": 0,
  "licenses": [
    "The Apache Software License, Version 2.0"
  ],
  "categories": [
    "Uncategorized"
  ],
  "dsv": 1
}