{
  "id": "pkg:maven/org.noear/solon.sessionstate.local",
  "description": "Java project for solon",
  "group_id": "org.noear",
  "artifact_id": "solon.sessionstate.local",
  "version_latest": "3.5.1-M2",
  "ts_publish": 1755851782000,
  "dt_publish": "2025-08-22 16:36:22.000",
  "ts_update": 1755852953268,
  "dt_update": "2025-08-22 16:55:53.268",
  "count_dep": 1,
  "count_ref": 0,
  "licenses": [
    "The Apache Software License, Version 2.0"
  ],
  "categories": [
    "Uncategorized"
  ],
  "dsv": 1
}