{
  "id": "pkg:maven/com.onfido.sdk/translations-profileData-nl-nl",
  "description": "translations-profileData-nl-nl",
  "group_id": "com.onfido.sdk",
  "artifact_id": "translations-profileData-nl-nl",
  "version_latest": "0.0.18",
  "ts_publish": 1758104943000,
  "dt_publish": "2025-09-17 18:29:03.000",
  "ts_update": 1758108386292,
  "dt_update": "2025-09-17 19:26:26.292",
  "count_dep": 0,
  "count_ref": 0,
  "licenses": [
    "Onfido Android SDK License"
  ],
  "categories": null,
  "dsv": 1
}