{
	"id":"pkg:maven/software.visionary.temper/immutable-fahrenheit",
	"description":"Visionary Software Solutions: Immutable Fahrenheit",
	"group_id":"software.visionary.temper",
	"artifact_id":"immutable-fahrenheit",
	"version_latest":"2025.08.20",
	"ts_publish":1757099598000,
	"dt_publish":"2025-09-06 03:13:18.000",
	"ts_update":1757101471969,
	"dt_update":"2025-09-06 03:44:21.569",
	"count_dep":2,
	"count_ref":0,
	"licenses":[
		"GNU General Public License, v 3.0 or later"
	],
	"dsv":1,
	"url_project":"https://codeberg.org/Kompuwiz/temper",
	"url_oss_index":"https://ossindex.sonatype.org/component/pkg:maven/software.visionary.temper/immutable-fahrenheit@2025.08.20",
	"contributors":[
		"Nico Vaidyanathan Hidalgo"
	],
	"url_scm":"https://codeberg.org/Kompuwiz/temper"
}