{
  "id": "pkg:maven/io.github.tillhub/payment-engine-core",
  "description": "Kotlin MultiPlatform Library that combines various payment implementations into a single, easy-to-use interface",
  "group_id": "io.github.tillhub",
  "artifact_id": "payment-engine-core",
  "version_latest": "4.0.0",
  "ts_publish": 1758881649000,
  "dt_publish": "2025-09-26 18:14:09.000",
  "ts_update": 1758882372155,
  "dt_update": "2025-09-26 18:26:12.155",
  "count_dep": 6,
  "count_ref": 1,
  "licenses": [
    "MIT"
  ],
  "categories": null,
  "dsv": 1
}