{
  "id": "pkg:maven/io.github.thearchitect123/titansocket-jvm",
  "description": "A kotlin multiplatform implementation of a websocket. Supports both iOS & Android",
  "group_id": "io.github.thearchitect123",
  "artifact_id": "titansocket-jvm",
  "version_latest": "0.3.2",
  "ts_publish": 1756050924000,
  "dt_publish": "2025-08-24 23:55:24.000",
  "ts_update": 1756052745826,
  "dt_update": "2025-08-25 00:25:45.826",
  "count_dep": 4,
  "count_ref": 0,
  "licenses": [
    "MIT"
  ],
  "categories": null,
  "dsv": 1
}