{
  "id": "pkg:maven/org.apache.druid.extensions.contrib/druid-virtual-columns",
  "description": "druid-virtual-columns",
  "group_id": "org.apache.druid.extensions.contrib",
  "artifact_id": "druid-virtual-columns",
  "version_latest": "34.0.0",
  "ts_publish": 1754346925000,
  "dt_publish": "2025-08-05 06:35:25.000",
  "ts_update": 1757780159593,
  "dt_update": "2025-09-14 00:15:59.593",
  "count_dep": 87,
  "count_ref": 0,
  "licenses": [
    "Apache License, Version 2.0"
  ],
  "categories": [
    "Uncategorized"
  ],
  "dsv": 1
}