{
  "id": "pkg:maven/io.mosip.certify/postgres-dataprovider-plugin",
  "description": "Data provider plugin implementation through postgres db that is used to showcase the integration with certify",
  "group_id": "io.mosip.certify",
  "artifact_id": "postgres-dataprovider-plugin",
  "version_latest": "0.5.0",
  "ts_publish": 1756188392000,
  "dt_publish": "2025-08-26 14:06:32.000",
  "ts_update": 1756189423692,
  "dt_update": "2025-08-26 14:23:43.692",
  "count_dep": 109,
  "count_ref": 0,
  "licenses": [
    "MPL 2.0"
  ],
  "categories": null,
  "dsv": 1
}