{
  "id": "pkg:maven/cash.atto/commons-core-jvm",
  "description": "Atto Commons Core provides a set of low-level operations that includes signing, seed generation, block hashing, and account creation.",
  "group_id": "cash.atto",
  "artifact_id": "commons-core-jvm",
  "version_latest": "5.3.0",
  "ts_publish": 1758199956000,
  "dt_publish": "2025-09-18 20:52:36.000",
  "ts_update": 1758200822611,
  "dt_update": "2025-09-18 21:07:02.611",
  "count_dep": 13,
  "count_ref": 11,
  "licenses": [
    "BSD 3-Clause License"
  ],
  "categories": null,
  "dsv": 1
}