{
  "id": "pkg:maven/com.qcloud/chdfs_hadoop_plugin_network",
  "description": "Tencent Qcloud chdfs hadoop plugins.",
  "group_id": "com.qcloud",
  "artifact_id": "chdfs_hadoop_plugin_network",
  "version_latest": "3.7",
  "ts_publish": 1757300398000,
  "dt_publish": "2025-09-08 10:59:58.000",
  "ts_update": 1757301955887,
  "dt_update": "2025-09-08 11:25:55.887",
  "count_dep": 63,
  "count_ref": 0,
  "licenses": [
    "chdfs-hadoop-plugin"
  ],
  "categories": [
    "Cloud Computing"
  ],
  "dsv": 1
}