{
  "id": "pkg:maven/io.github.rzo1.org.sweble.wom3/sweble-wom3-example-basic",
  "description": "An example project that contains a simple application that is able to parse\n\t\ta page written in Wikitext and render it as HTML or plain text.",
  "group_id": "io.github.rzo1.org.sweble.wom3",
  "artifact_id": "sweble-wom3-example-basic",
  "version_latest": "4.0.1",
  "ts_publish": 1758184166000,
  "dt_publish": "2025-09-18 16:29:26.000",
  "ts_update": 1758184886640,
  "dt_update": "2025-09-18 16:41:26.640",
  "count_dep": 23,
  "count_ref": 0,
  "licenses": [
    "The Apache Software License, Version 2.0"
  ],
  "categories": null,
  "dsv": 1
}