{
	"ts_update":1755472514267,
	"url_project":"https://www.mojohaus.org/mojo-parent",
	"url_oss_index":"https://ossindex.sonatype.org/component/pkg:maven/org.codehaus.mojo/mojo-parent@93",
	"url_issue_management":"https://github.com/mojohaus/mojo-parent/issues",
	"contributors":[
		"Arnaud Heritier",
		"Karl-Heinz Marbaise",
		"Baptiste Mathus",
		"David Karlsen",
		"Mirko Friedenhagen",
		"Slawomir Jaranowski",
		"Hervé Boutemy",
		"Evgeny Mandrikov",
		"Lennart Jörelid",
		"Sylwester Lachiewicz",
		"Anders Hammar",
		"Olivier Lamy"
	],
	"url_scm":"https://github.com/mojohaus/mojo-parent/tree/93",
	"url_ci_management":"https://github.com/mojohaus/mojo-parent/actions"
}