{
  "id": "pkg:maven/app.cash.wisp/wisp-feature",
  "description": "a module containing feature flag helpers",
  "group_id": "app.cash.wisp",
  "artifact_id": "wisp-feature",
  "version_latest": "2025.09.19.204155-e5a6013",
  "ts_publish": 1758315870000,
  "dt_publish": "2025-09-20 05:04:30.000",
  "ts_update": 1758317164995,
  "dt_update": "2025-09-20 05:26:04.995",
  "count_dep": 3,
  "count_ref": 5,
  "licenses": [
    "The Apache Software License, Version 2.0"
  ],
  "categories": [
    "Uncategorized"
  ],
  "dsv": 1
}