{
  "id": "pkg:maven/app.cash.wisp/wisp-task",
  "description": "a module containing task related helpers",
  "group_id": "app.cash.wisp",
  "artifact_id": "wisp-task",
  "version_latest": "2025.08.15.045554-3579373",
  "ts_publish": 1755235193000,
  "dt_publish": "2025-08-15 13:19:53.000",
  "ts_update": 1755237069688,
  "dt_update": "2025-08-15 13:51:09.688",
  "count_dep": 15,
  "count_ref": 0,
  "licenses": [
    "The Apache Software License, Version 2.0"
  ],
  "categories": [
    "Uncategorized"
  ],
  "dsv": 1
}