{
  "id": "pkg:maven/it.unibo.collektive/gradle-plugin",
  "description": "Gradle support for the Collektive Kotlin compiler plugin performing automatic aggregate alignment of Kotlin sources",
  "group_id": "it.unibo.collektive",
  "artifact_id": "gradle-plugin",
  "version_latest": "26.1.1-dev03+027202d",
  "ts_publish": 1754617839000,
  "dt_publish": "2025-08-08 09:50:39.000",
  "ts_update": 1754618151962,
  "dt_update": "2025-08-08 09:55:51.962",
  "count_dep": 3,
  "count_ref": 1,
  "licenses": [
    "Apache License 2.0"
  ],
  "categories": null,
  "dsv": 1
}