{
	"id":"pkg:maven/ai.tock/tock-nlp-front-client",
	"description":"Client interface for Tock NLP Front",
	"group_id":"ai.tock",
	"artifact_id":"tock-nlp-front-client",
	"version_latest":"25.3.10",
	"ts_publish":1755507213000,
	"dt_publish":"2025-08-18 16:53:33.000",
	"ts_update":1755508958933,
	"dt_update":"2025-08-18 17:21:15.463",
	"count_dep":7,
	"count_ref":2,
	"licenses":[],
	"categories":[
		"Uncategorized"
	],
	"dsv":1,
	"url_oss_index":"https://ossindex.sonatype.org/component/pkg:maven/ai.tock/tock-nlp-front-client@25.3.10"
}