{
  "id": "pkg:maven/com.scaleoutsoftware/invocationgrid",
  "description": "Invocation Grid Hosting API for creating invocation grids on ScaleOut Software’s family of in-memory computing products.",
  "group_id": "com.scaleoutsoftware",
  "artifact_id": "invocationgrid",
  "version_latest": "3.0.0",
  "ts_publish": 1757958489000,
  "dt_publish": "2025-09-16 01:48:09.000",
  "ts_update": 1757960485280,
  "dt_update": "2025-09-16 02:21:25.280",
  "count_dep": 15,
  "count_ref": 0,
  "licenses": [
    "ScaleOut EULA"
  ],
  "categories": null,
  "dsv": 1
}