{
  "id": "pkg:maven/io.github.ackeecz/ackeelities-coroutines-android",
  "description": "Coroutines artifact of the Ackeelities library. Contains utilities related to coroutines.",
  "group_id": "io.github.ackeecz",
  "artifact_id": "ackeelities-coroutines-android",
  "version_latest": "1.0.0",
  "ts_publish": 1755103065000,
  "dt_publish": "2025-08-14 00:37:45.000",
  "ts_update": 1755103943625,
  "dt_update": "2025-08-14 00:52:23.625",
  "count_dep": 3,
  "count_ref": 0,
  "licenses": [
    "The Apache Software License, Version 2.0"
  ],
  "categories": [
    "Uncategorized"
  ],
  "dsv": 1
}