{
  "id": "pkg:maven/io.github.zj565061763.kmp/mutator-iosx64",
  "description": "Kotlin Multiplatform Mutex Operation library.",
  "group_id": "io.github.zj565061763.kmp",
  "artifact_id": "mutator-iosx64",
  "version_latest": "1.4.0",
  "ts_publish": 1757700300000,
  "dt_publish": "2025-09-13 02:05:00.000",
  "ts_update": 1757701284023,
  "dt_update": "2025-09-13 02:21:24.023",
  "count_dep": 2,
  "count_ref": 0,
  "licenses": [
    "The Apache Software License, Version 2.0"
  ],
  "categories": null,
  "dsv": 1
}