{
  "id": "pkg:maven/org.apache.camel/camel-cxf-spring-soap",
  "description": "Camel CXF SOAP Spring support",
  "group_id": "org.apache.camel",
  "artifact_id": "camel-cxf-spring-soap",
  "version_latest": "4.14.0",
  "ts_publish": 1755263182000,
  "dt_publish": "2025-08-15 21:06:22.000",
  "ts_update": 1758385029382,
  "dt_update": "2025-09-21 00:17:09.382",
  "count_dep": 0,
  "count_ref": 3,
  "licenses": [
    "Apache-2.0"
  ],
  "categories": [
    "Enterprise Integration"
  ],
  "dsv": 1
}