{
  "id": "pkg:maven/org.apache.camel/camel-xmlsecurity",
  "description": "Camel Partial XML Encryption/Decryption and XML Signature support",
  "group_id": "org.apache.camel",
  "artifact_id": "camel-xmlsecurity",
  "version_latest": "4.13.0",
  "ts_publish": 1751643011000,
  "dt_publish": "2025-07-04 23:30:11.000",
  "ts_update": 1754517763380,
  "dt_update": "2025-08-07 06:02:43.380",
  "count_dep": 8,
  "count_ref": 4,
  "licenses": [
    "Apache-2.0"
  ],
  "categories": [
    "Enterprise Integration"
  ],
  "dsv": 1
}