{
  "id": "pkg:maven/org.apache.camel/camel-protobuf",
  "description": "Camel Google Protobuf data format support",
  "group_id": "org.apache.camel",
  "artifact_id": "camel-protobuf",
  "version_latest": "4.13.0",
  "ts_publish": 1751642308000,
  "dt_publish": "2025-07-04 23:18:28.000",
  "ts_update": 1754517761480,
  "dt_update": "2025-08-07 06:02:41.480",
  "count_dep": 4,
  "count_ref": 4,
  "licenses": [
    "Apache-2.0"
  ],
  "categories": [
    "Enterprise Integration"
  ],
  "dsv": 1
}