{
  "id": "pkg:maven/net.xdob.ratly/ratly-rmap",
  "description": "Distributed Database with Strong Consistency Based on Raft Protocol",
  "group_id": "net.xdob.ratly",
  "artifact_id": "ratly-rmap",
  "version_latest": "3.7.0",
  "ts_publish": 1757990725000,
  "dt_publish": "2025-09-16 10:45:25.000",
  "ts_update": 1757994125639,
  "dt_update": "2025-09-16 11:42:05.639",
  "count_dep": 43,
  "count_ref": 0,
  "licenses": [
    "The Apache License, Version 2.0"
  ],
  "categories": null,
  "dsv": 1
}