{
  "id": "pkg:maven/de.lars-sh/parent",
  "description": "This parent POM is made for great Java projects, handling \n\t\tEclipse and optional Project Lombok integration, having consistent Checkstyle \n\t\tand SpotBugs (successor of FindBugs) definitions in addition to even more \n\t\tMaven pre-configuration.",
  "group_id": "de.lars-sh",
  "artifact_id": "parent",
  "version_latest": "0.9.18",
  "ts_publish": 1757611918000,
  "dt_publish": "2025-09-12 01:31:58.000",
  "ts_update": 1757612666952,
  "dt_update": "2025-09-12 01:44:26.952",
  "count_dep": 11,
  "count_ref": 0,
  "licenses": [
    "MIT License"
  ],
  "categories": [
    "Uncategorized"
  ],
  "dsv": 1
}