{
  "id": "pkg:maven/it.unibo.tuprolog/solve-problog-js",
  "description": "State-machine-based implementation of ProbLog",
  "group_id": "it.unibo.tuprolog",
  "artifact_id": "solve-problog-js",
  "version_latest": "1.1.1",
  "ts_publish": 1758230237000,
  "dt_publish": "2025-09-19 05:17:17.000",
  "ts_update": 1758230765418,
  "dt_update": "2025-09-19 05:26:05.418",
  "count_dep": 6,
  "count_ref": 1,
  "licenses": [
    "Apache-2.0"
  ],
  "categories": [
    "Uncategorized"
  ],
  "dsv": 1
}