{
  "id": "pkg:maven/com.yahoo.vespa/vespa-3party-jars",
  "description": "List 3rd party Java libraries that should be installed to lib/jars.\n        These libraries are not embedded in fat jars produced by bundle-plugin's 'assemble-fat-jar' goal.",
  "group_id": "com.yahoo.vespa",
  "artifact_id": "vespa-3party-jars",
  "version_latest": "8.562.17",
  "ts_publish": 1754983051000,
  "dt_publish": "2025-08-12 15:17:31.000",
  "ts_update": 1754983551047,
  "dt_update": "2025-08-12 15:25:51.047",
  "count_dep": 20,
  "count_ref": 0,
  "licenses": [
    "The Apache License, Version 2.0"
  ],
  "categories": [
    "Big Data",
    "Parallel Data Processing"
  ],
  "dsv": 1
}