{
  "id": "pkg:maven/io.github.opensabe-tech/spring-boot-starter-cache",
  "description": "spring-boot-starter-cache",
  "group_id": "io.github.opensabe-tech",
  "artifact_id": "spring-boot-starter-cache",
  "version_latest": "2.0.0-theta",
  "ts_publish": 1756979489000,
  "dt_publish": "2025-09-04 17:51:29.000",
  "ts_update": 1756980954376,
  "dt_update": "2025-09-04 18:15:54.376",
  "count_dep": 101,
  "count_ref": 0,
  "licenses": [
    "Apache License, Version 2.0"
  ],
  "categories": null,
  "dsv": 1
}