{
  "id": "pkg:maven/com.intuit.playerui/hermes-android",
  "description": "A cross-platform semantic rendering engine",
  "group_id": "com.intuit.playerui",
  "artifact_id": "hermes-android",
  "version_latest": "0.14.0-next.2",
  "ts_publish": 1756500458000,
  "dt_publish": "2025-08-30 04:47:38.000",
  "ts_update": 1756502008465,
  "dt_update": "2025-08-30 05:13:28.465",
  "count_dep": 13,
  "count_ref": 0,
  "licenses": [
    "Apache License, Version 2.0"
  ],
  "categories": null,
  "dsv": 1
}