{
	"id":"pkg:maven/us.craigmiller160/publish-practice",
	"description":"A simple project to test publishing to Maven Central",
	"group_id":"us.craigmiller160",
	"artifact_id":"publish-practice",
	"version_latest":"0.0.5",
	"ts_publish":1756407675000,
	"dt_publish":"2025-08-29 03:01:15.000",
	"ts_update":1756408433657,
	"dt_update":"2025-08-29 03:12:31.386",
	"count_dep":0,
	"count_ref":0,
	"licenses":[
		"The Apache License, Version 2.0"
	],
	"dsv":1,
	"url_project":"https://gitlab.com/craigmiller1601/publish-practice",
	"url_oss_index":"https://ossindex.sonatype.org/component/pkg:maven/us.craigmiller160/publish-practice@0.0.1",
	"contributors":[
		"Craig Miller"
	],
	"url_scm":"https://gitlab.com/craigmiller1601/publish-practice"
}